{
  "saved_at": "2026-06-21 03:41:20",
  "key": "entry_url",
  "rc_date": "20260621",
  "meet": "서울",
  "race_no": 1,
  "msg": "OK",
  "rows": [
    {
      "age": "2",
      "ageCond": "2세",
      "budam": "별정A",
      "calPrizeY": "0",
      "calPrize_6m": "0",
      "chaksun1": "24750000",
      "chaksun2": "9900000",
      "chaksun3": "6300000",
      "chaksun4": "2250000",
      "chaksun5": "1800000",
      "chaksunT": "1800000",
      "enNo": "4",
      "hrName": "블리츠카라",
      "hrNo": "0057821",
      "meet": "서울",
      "name": "한국",
      "owName": "명주환",
      "owNo": "123020",
      "pgDate": "20260530",
      "pgNo": "1",
      "prdName": "배병재",
      "prizeCond": "R0~0",
      "rank": "국6등급",
      "rcCntY": "1",
      "rcDist": "1000",
      "rcName": "일반",
      "sex": "수",
      "trName": "임채덕",
      "trNo": "070198",
      "recentRating": "nan"
    },
    {
      "age": "2",
      "ageCond": "2세",
      "budam": "별정A",
      "calPrizeY": "0",
      "calPrize_6m": "0",
      "chaksun1": "24750000",
      "chaksun2": "9900000",
      "chaksun3": "6300000",
      "chaksun4": "2250000",
      "chaksun5": "1800000",
      "chaksunT": "0",
      "enNo": "9",
      "hrName": "나르샤루시",
      "hrNo": "0055280",
      "meet": "서울",
      "name": "한국",
      "owName": "(주)아진화학",
      "owNo": "125010",
      "pgDate": "20260530",
      "pgNo": "1",
      "prdName": "김홍대",
      "prizeCond": "R0~0",
      "rank": "국6등급",
      "rcCntY": "1",
      "rcDist": "1000",
      "rcName": "일반",
      "sex": "암",
      "trName": "정호익",
      "trNo": "070148",
      "recentRating": "nan"
    },
    {
      "age": "2",
      "ageCond": "2세",
      "budam": "별정A",
      "calPrizeY": "0",
      "calPrize_6m": "0",
      "chaksun1": "24750000",
      "chaksun2": "9900000",
      "chaksun3": "6300000",
      "chaksun4": "2250000",
      "chaksun5": "1800000",
      "chaksunT": "2250000",
      "enNo": "10",
      "hrName": "뉴발삭스",
      "hrNo": "0055301",
      "meet": "서울",
      "name": "한국",
      "owName": "김창식",
      "owNo": "010352",
      "pgDate": "20260530",
      "pgNo": "1",
      "prdName": "김순건",
      "prizeCond": "R0~0",
      "rank": "국6등급",
      "rcCntY": "1",
      "rcDist": "1000",
      "rcName": "일반",
      "sex": "수",
      "trName": "이관호",
      "trNo": "070181",
      "recentRating": "nan"
    },
    {
      "age": "2",
      "ageCond": "2세",
      "budam": "별정A",
      "calPrizeY": "0",
      "calPrize_6m": "0",
      "chaksun1": "24750000",
      "chaksun2": "9900000",
      "chaksun3": "6300000",
      "chaksun4": "2250000",
      "chaksun5": "1800000",
      "chaksunT": "9900000",
      "enNo": "11",
      "hrName": "로드투챔피언",
      "hrNo": "0057009",
      "meet": "서울",
      "name": "한국",
      "owName": "최종복",
      "owNo": "065126",
      "pgDate": "20260530",
      "pgNo": "1",
      "prdName": "최민석",
      "prizeCond": "R0~0",
      "rank": "국6등급",
      "rcCntY": "1",
      "rcDist": "1000",
      "rcName": "일반",
      "sex": "수",
      "trName": "정호익",
      "trNo": "070148",
      "recentRating": "nan"
    },
    {
      "age": "2",
      "ageCond": "2세",
      "budam": "별정A",
      "calPrizeY": "0",
      "calPrize_6m": "0",
      "chaksun1": "24750000",
      "chaksun2": "9900000",
      "chaksun3": "6300000",
      "chaksun4": "2250000",
      "chaksun5": "1800000",
      "chaksunT": "24750000",
      "enNo": "36",
      "hrName": "메이저퓨리",
      "hrNo": "0055781",
      "meet": "서울",
      "name": "한국",
      "owName": "정영광",
      "owNo": "104117",
      "pgDate": "20260530",
      "pgNo": "1",
      "prdName": "(주)녹원목장",
      "prizeCond": "R0~0",
      "rank": "국6등급",
      "rcCntY": "1",
      "rcDist": "1000",
      "rcName": "일반",
      "sex": "수",
      "trName": "김동균",
      "trNo": "070170",
      "recentRating": "nan"
    },
    {
      "age": "2",
      "ageCond": "2세",
      "budam": "별정A",
      "calPrizeY": "0",
      "calPrize_6m": "0",
      "chaksun1": "24750000",
      "chaksun2": "9900000",
      "chaksun3": "6300000",
      "chaksun4": "2250000",
      "chaksun5": "1800000",
      "chaksunT": "0",
      "enNo": "37",
      "hrName": "블루호라이즌",
      "hrNo": "0055740",
      "meet": "서울",
      "name": "한국",
      "owName": "페가수스",
      "owNo": "065127",
      "pgDate": "20260530",
      "pgNo": "1",
      "prdName": "페가수스",
      "prizeCond": "R0~0",
      "rank": "국6등급",
      "rcCntY": "1",
      "rcDist": "1000",
      "rcName": "일반",
      "sex": "암",
      "trName": "토니",
      "trNo": "070265",
      "recentRating": "nan"
    },
    {
      "age": "2",
      "ageCond": "2세",
      "budam": "별정A",
      "calPrizeY": "0",
      "calPrize_6m": "0",
      "chaksun1": "24750000",
      "chaksun2": "9900000",
      "chaksun3": "6300000",
      "chaksun4": "2250000",
      "chaksun5": "1800000",
      "chaksunT": "2250000",
      "enNo": "54",
      "hrName": "그랜드폭풍",
      "hrNo": "0055300",
      "meet": "서울",
      "name": "한국",
      "owName": "박재범",
      "owNo": "104040",
      "pgDate": "20260530",
      "pgNo": "1",
      "prdName": "김순건",
      "prizeCond": "R0~0",
      "rank": "국6등급",
      "rcCntY": "1",
      "rcDist": "1000",
      "rcName": "일반",
      "sex": "암",
      "trName": "박재우",
      "trNo": "070164",
      "recentRating": "nan"
    },
    {
      "age": "2",
      "ageCond": "2세",
      "budam": "별정A",
      "calPrizeY": "0",
      "calPrize_6m": "0",
      "chaksun1": "24750000",
      "chaksun2": "9900000",
      "chaksun3": "6300000",
      "chaksun4": "2250000",
      "chaksun5": "1800000",
      "chaksunT": "6300000",
      "enNo": "55",
      "hrName": "퀸즈임팩트",
      "hrNo": "0055485",
      "meet": "서울",
      "name": "한국",
      "owName": "박남성",
      "owNo": "010496",
      "pgDate": "20260530",
      "pgNo": "1",
      "prdName": "오공학",
      "prizeCond": "R0~0",
      "rank": "국6등급",
      "rcCntY": "1",
      "rcDist": "1000",
      "rcName": "일반",
      "sex": "암",
      "trName": "박재우",
      "trNo": "070164",
      "recentRating": "nan"
    },
    {
      "age": "2",
      "ageCond": "2세",
      "budam": "별정A",
      "calPrizeY": "0",
      "calPrize_6m": "0",
      "chaksun1": "24750000",
      "chaksun2": "9900000",
      "chaksun3": "6300000",
      "chaksun4": "2250000",
      "chaksun5": "1800000",
      "chaksunT": "0",
      "enNo": "114",
      "hrName": "루움축제",
      "hrNo": "0056677",
      "meet": "서울",
      "name": "한국",
      "owName": "김종근",
      "owNo": "122022",
      "pgDate": "20260530",
      "pgNo": "1",
      "prdName": "김호균",
      "prizeCond": "R0~0",
      "rank": "국6등급",
      "rcCntY": "1",
      "rcDist": "1000",
      "rcName": "일반",
      "sex": "암",
      "trName": "안병기",
      "trNo": "070146",
      "recentRating": "nan"
    },
    {
      "age": "2",
      "ageCond": "2세",
      "budam": "별정A",
      "calPrizeY": "0",
      "calPrize_6m": "0",
      "chaksun1": "24750000",
      "chaksun2": "9900000",
      "chaksun3": "6300000",
      "chaksun4": "2250000",
      "chaksun5": "1800000",
      "chaksunT": "0",
      "enNo": "116",
      "hrName": "글로벌최강",
      "hrNo": "0055703",
      "meet": "서울",
      "name": "한국",
      "owName": "김준현",
      "owNo": "106289",
      "pgDate": "20260530",
      "pgNo": "1",
      "prdName": "농업회사법인 주식회사 연학",
      "prizeCond": "R0~0",
      "rank": "국6등급",
      "rcCntY": "1",
      "rcDist": "1000",
      "rcName": "일반",
      "sex": "수",
      "trName": "안병기",
      "trNo": "070146",
      "recentRating": "nan"
    },
    {
      "age": "2",
      "ageCond": "2세",
      "budam": "별정A",
      "calPrizeY": "0",
      "calPrize_6m": "0",
      "chaksun1": "24750000",
      "chaksun2": "9900000",
      "chaksun3": "6300000",
      "chaksun4": "2250000",
      "chaksun5": "1800000",
      "chaksunT": "0",
      "enNo": "127",
      "hrName": "남경스피닝",
      "hrNo": "0056847",
      "meet": "서울",
      "name": "한국",
      "owName": "남경",
      "owNo": "125007",
      "pgDate": "20260530",
      "pgNo": "1",
      "prdName": "박승현",
      "prizeCond": "R0~0",
      "rank": "국6등급",
      "rcCntY": "1",
      "rcDist": "1000",
      "rcName": "일반",
      "sex": "암",
      "trName": "최봉주",
      "trNo": "070152",
      "recentRating": "nan"
    },
    {
      "age": "2",
      "ageCond": "2세",
      "budam": "별정A",
      "calPrizeY": "0",
      "calPrize_6m": "0",
      "chaksun1": "24750000",
      "chaksun2": "9900000",
      "chaksun3": "6300000",
      "chaksun4": "2250000",
      "chaksun5": "1800000",
      "chaksunT": "0",
      "enNo": "128",
      "hrName": "가온의빛",
      "hrNo": "0055947",
      "meet": "서울",
      "name": "한국",
      "owName": "이경헌",
      "owNo": "124041",
      "pgDate": "20260530",
      "pgNo": "1",
      "prdName": "이경하",
      "prizeCond": "R0~0",
      "rank": "국6등급",
      "rcCntY": "1",
      "rcDist": "1000",
      "rcName": "일반",
      "sex": "암",
      "trName": "최봉주",
      "trNo": "070152",
      "recentRating": "nan"
    },
    {
      "age": "3",
      "ageCond": "연령오픈",
      "budam": "별정A",
      "calPrizeY": "0",
      "calPrize_6m": "0",
      "chaksun1": "16500000",
      "chaksun2": "6600000",
      "chaksun3": "4200000",
      "chaksun4": "1500000",
      "chaksun5": "1200000",
      "chaksunT": "0",
      "enNo": "5",
      "hrName": "컴퍼스포스",
      "hrNo": "0053825",
      "meet": "서울",
      "name": "한국",
      "owName": "이상진",
      "owNo": "122030",
      "pgDate": "20260530",
      "pgNo": "2",
      "prdName": "농업회사법인주식회사홀스앤",
      "prizeCond": "R0~0",
      "rank": "국6등급",
      "rcCntY": "7",
      "rcDist": "1300",
      "rcName": "일반",
      "sex": "암",
      "trName": "임채덕",
      "trNo": "070198",
      "recentRating": "0"
    },
    {
      "age": "3",
      "ageCond": "연령오픈",
      "budam": "별정A",
      "calPrizeY": "6450000",
      "calPrize_6m": "2700000",
      "chaksun1": "16500000",
      "chaksun2": "6600000",
      "chaksun3": "4200000",
      "chaksun4": "1500000",
      "chaksun5": "1200000",
      "chaksunT": "7950000",
      "enNo": "12",
      "hrName": "로드투퍼펙트",
      "hrNo": "0054191",
      "meet": "서울",
      "name": "한국",
      "owName": "최종복",
      "owNo": "065126",
      "pgDate": "20260530",
      "pgNo": "2",
      "prdName": "최민석",
      "prizeCond": "R0~0",
      "rank": "국6등급",
      "rcCntY": "6",
      "rcDist": "1300",
      "rcName": "일반",
      "sex": "암",
      "trName": "정호익",
      "trNo": "070148",
      "recentRating": "0"
    },
    {
      "age": "3",
      "ageCond": "연령오픈",
      "budam": "별정A",
      "calPrizeY": "12750000",
      "calPrize_6m": "12750000",
      "chaksun1": "16500000",
      "chaksun2": "6600000",
      "chaksun3": "4200000",
      "chaksun4": "1500000",
      "chaksun5": "1200000",
      "chaksunT": "29250000",
      "enNo": "14",
      "hrName": "바람개비",
      "hrNo": "0053229",
      "meet": "서울",
      "name": "한국",
      "owName": "선형조",
      "owNo": "121055",
      "pgDate": "20260530",
      "pgNo": "2",
      "prdName": "선경래",
      "prizeCond": "R0~0",
      "rank": "국6등급",
      "rcCntY": "4",
      "rcDist": "1300",
      "rcName": "일반",
      "sex": "수",
      "trName": "신삼영",
      "trNo": "070161",
      "recentRating": "0"
    },
    {
      "age": "3",
      "ageCond": "연령오픈",
      "budam": "별정A",
      "calPrizeY": "5550000",
      "calPrize_6m": "5550000",
      "chaksun1": "16500000",
      "chaksun2": "6600000",
      "chaksun3": "4200000",
      "chaksun4": "1500000",
      "chaksun5": "1200000",
      "chaksunT": "22050000",
      "enNo": "20",
      "hrName": "비트코드",
      "hrNo": "0054522",
      "meet": "서울",
      "name": "한국",
      "owName": "황은호",
      "owNo": "111007",
      "pgDate": "20260530",
      "pgNo": "2",
      "prdName": "김정철",
      "prizeCond": "R0~0",
      "rank": "국6등급",
      "rcCntY": "4",
      "rcDist": "1300",
      "rcName": "일반",
      "sex": "암",
      "trName": "이관호",
      "trNo": "070181",
      "recentRating": "0"
    },
    {
      "age": "3",
      "ageCond": "연령오픈",
      "budam": "별정A",
      "calPrizeY": "1200000",
      "calPrize_6m": "1200000",
      "chaksun1": "16500000",
      "chaksun2": "6600000",
      "chaksun3": "4200000",
      "chaksun4": "1500000",
      "chaksun5": "1200000",
      "chaksunT": "7800000",
      "enNo": "39",
      "hrName": "레이스디바",
      "hrNo": "0053267",
      "meet": "서울",
      "name": "한국",
      "owName": "이민정",
      "owNo": "125002",
      "pgDate": "20260530",
      "pgNo": "2",
      "prdName": "이광림",
      "prizeCond": "R0~0",
      "rank": "국6등급",
      "rcCntY": "4",
      "rcDist": "1300",
      "rcName": "일반",
      "sex": "암",
      "trName": "토니",
      "trNo": "070265",
      "recentRating": "0"
    },
    {
      "age": "3",
      "ageCond": "연령오픈",
      "budam": "별정A",
      "calPrizeY": "6600000",
      "calPrize_6m": "6600000",
      "chaksun1": "16500000",
      "chaksun2": "6600000",
      "chaksun3": "4200000",
      "chaksun4": "1500000",
      "chaksun5": "1200000",
      "chaksunT": "6600000",
      "enNo": "50",
      "hrName": "다나은리치",
      "hrNo": "0053591",
      "meet": "서울",
      "name": "한국",
      "owName": "이진경",
      "owNo": "117021",
      "pgDate": "20260530",
      "pgNo": "2",
      "prdName": "이경우",
      "prizeCond": "R0~0",
      "rank": "국6등급",
      "rcCntY": "4",
      "rcDist": "1300",
      "rcName": "일반",
      "sex": "암",
      "trName": "박천서",
      "trNo": "070115",
      "recentRating": "0"
    },
    {
      "age": "4",
      "ageCond": "연령오픈",
      "budam": "별정A",
      "calPrizeY": "0",
      "calPrize_6m": "0",
      "chaksun1": "16500000",
      "chaksun2": "6600000",
      "chaksun3": "4200000",
      "chaksun4": "1500000",
      "chaksun5": "1200000",
      "chaksunT": "0",
      "enNo": "113",
      "hrName": "래피드스톰",
      "hrNo": "0050892",
      "meet": "서울",
      "name": "한국",
      "owName": "코리아호스랜드",
      "owNo": "065134",
      "pgDate": "20260530",
      "pgNo": "2",
      "prdName": "(주)코리아호스랜드",
      "prizeCond": "R0~0",
      "rank": "국6등급",
      "rcCntY": "1",
      "rcDist": "1300",
      "rcName": "일반",
      "sex": "암",
      "trName": "구자흥",
      "trNo": "070157",
      "recentRating": "nan"
    },
    {
      "age": "3",
      "ageCond": "연령오픈",
      "budam": "별정A",
      "calPrizeY": "2250000",
      "calPrize_6m": "2250000",
      "chaksun1": "16500000",
      "chaksun2": "6600000",
      "chaksun3": "4200000",
      "chaksun4": "1500000",
      "chaksun5": "1200000",
      "chaksunT": "2250000",
      "enNo": "145",
      "hrName": "플레이매치",
      "hrNo": "0053561",
      "meet": "서울",
      "name": "한국",
      "owName": "간용기",
      "owNo": "123031",
      "pgDate": "20260530",
      "pgNo": "2",
      "prdName": "정경애",
      "prizeCond": "R0~0",
      "rank": "국6등급",
      "rcCntY": "1",
      "rcDist": "1300",
      "rcName": "일반",
      "sex": "수",
      "trName": "최용구",
      "trNo": "070168",
      "recentRating": "0"
    },
    {
      "age": "3",
      "ageCond": "연령오픈",
      "budam": "별정A",
      "calPrizeY": "0",
      "calPrize_6m": "0",
      "chaksun1": "16500000",
      "chaksun2": "6600000",
      "chaksun3": "4200000",
      "chaksun4": "1500000",
      "chaksun5": "1200000",
      "chaksunT": "0",
      "enNo": "160",
      "hrName": "금성샤이니",
      "hrNo": "0053345",
      "meet": "서울",
      "name": "한국",
      "owName": "조창규",
      "owNo": "065096",
      "pgDate": "20260530",
      "pgNo": "2",
      "prdName": "조창규",
      "prizeCond": "R0~0",
      "rank": "국6등급",
      "rcCntY": "2",
      "rcDist": "1300",
      "rcName": "일반",
      "sex": "암",
      "trName": "박재우",
      "trNo": "070164",
      "recentRating": "0"
    },
    {
      "age": "4",
      "ageCond": "연령오픈",
      "budam": "별정A",
      "calPrizeY": "1200000",
      "calPrize_6m": "1200000",
      "chaksun1": "16500000",
      "chaksun2": "6600000",
      "chaksun3": "4200000",
      "chaksun4": "1500000",
      "chaksun5": "1200000",
      "chaksunT": "2400000",
      "enNo": "178",
      "hrName": "슈퍼캔디",
      "hrNo": "0054471",
      "meet": "서울",
      "name": "한국",
      "owName": "(주)쎄쎄쎄",
      "owNo": "124017",
      "pgDate": "20260530",
      "pgNo": "2",
      "prdName": "권자수",
      "prizeCond": "R0~0",
      "rank": "국6등급",
      "rcCntY": "6",
      "rcDist": "1300",
      "rcName": "일반",
      "sex": "암",
      "trName": "이동국",
      "trNo": "070247",
      "recentRating": "0"
    },
    {
      "age": "3",
      "ageCond": "연령오픈",
      "budam": "별정A",
      "calPrizeY": "1800000",
      "calPrize_6m": "1800000",
      "chaksun1": "16500000",
      "chaksun2": "6600000",
      "chaksun3": "4200000",
      "chaksun4": "1500000",
      "chaksun5": "1200000",
      "chaksunT": "1800000",
      "enNo": "179",
      "hrName": "구름",
      "hrNo": "0053340",
      "meet": "서울",
      "name": "한국",
      "owName": "(주)쎄쎄쎄",
      "owNo": "124017",
      "pgDate": "20260530",
      "pgNo": "2",
      "prdName": "우림영농조합법인",
      "prizeCond": "R0~0",
      "rank": "국6등급",
      "rcCntY": "5",
      "rcDist": "1300",
      "rcName": "일반",
      "sex": "암",
      "trName": "이동국",
      "trNo": "070247",
      "recentRating": "0"
    },
    {
      "age": "3",
      "ageCond": "연령오픈",
      "budam": "별정A",
      "calPrizeY": "3450000",
      "calPrize_6m": "1200000",
      "chaksun1": "16500000",
      "chaksun2": "6600000",
      "chaksun3": "4200000",
      "chaksun4": "1500000",
      "chaksun5": "1200000",
      "chaksunT": "4650000",
      "enNo": "183",
      "hrName": "성실위너",
      "hrNo": "0053902",
      "meet": "서울",
      "name": "한국",
      "owName": "이동훈",
      "owNo": "104112",
      "pgDate": "20260530",
      "pgNo": "2",
      "prdName": "송용만",
      "prizeCond": "R0~0",
      "rank": "국6등급",
      "rcCntY": "5",
      "rcDist": "1300",
      "rcName": "일반",
      "sex": "암",
      "trName": "심승태",
      "trNo": "070166",
      "recentRating": "0"
    },
    {
      "age": "4",
      "ageCond": "연령오픈",
      "budam": "별정A",
      "calPrizeY": "0",
      "calPrize_6m": "0",
      "chaksun1": "16500000",
      "chaksun2": "6600000",
      "chaksun3": "4200000",
      "chaksun4": "1500000",
      "chaksun5": "1200000",
      "chaksunT": "1200000",
      "enNo": "207",
      "hrName": "피엔에스건즈",
      "hrNo": "0051136",
      "meet": "서울",
      "name": "한국",
      "owName": "피엔에스홈즈",
      "owNo": "118010",
      "pgDate": "20260530",
      "pgNo": "2",
      "prdName": "이병일",
      "prizeCond": "R0~0",
      "rank": "국6등급",
      "rcCntY": "7",
      "rcDist": "1300",
      "rcName": "일반",
      "sex": "암",
      "trName": "박윤규",
      "trNo": "070117",
      "recentRating": "0"
    },
    {
      "age": "4",
      "ageCond": "연령오픈",
      "budam": "별정A",
      "calPrizeY": "2400000",
      "calPrize_6m": "2400000",
      "chaksun1": "16500000",
      "chaksun2": "6600000",
      "chaksun3": "4200000",
      "chaksun4": "1500000",
      "chaksun5": "1200000",
      "chaksunT": "6600000",
      "enNo": "221",
      "hrName": "비바참",
      "hrNo": "0051316",
      "meet": "서울",
      "name": "한국",
      "owName": "김명식",
      "owNo": "010226",
      "pgDate": "20260530",
      "pgNo": "2",
      "prdName": "김명식",
      "prizeCond": "R0~0",
      "rank": "국6등급",
      "rcCntY": "3",
      "rcDist": "1300",
      "rcName": "일반",
      "sex": "암",
      "trName": "전승규",
      "trNo": "070182",
      "recentRating": "0"
    },
    {
      "age": "3",
      "ageCond": "연령오픈",
      "budam": "별정A",
      "calPrizeY": "12300000",
      "calPrize_6m": "12300000",
      "chaksun1": "16500000",
      "chaksun2": "6600000",
      "chaksun3": "4200000",
      "chaksun4": "1500000",
      "chaksun5": "1200000",
      "chaksunT": "18900000",
      "enNo": "229",
      "hrName": "빛나리즈",
      "hrNo": "0053637",
      "meet": "서울",
      "name": "한국",
      "owName": "(주)디알엠씨티",
      "owNo": "114026",
      "pgDate": "20260530",
      "pgNo": "2",
      "prdName": "이병일",
      "prizeCond": "R0~0",
      "rank": "국6등급",
      "rcCntY": "5",
      "rcDist": "1300",
      "rcName": "일반",
      "sex": "암",
      "trName": "박재우",
      "trNo": "070164",
      "recentRating": "0"
    },
    {
      "age": "3",
      "ageCond": "연령오픈",
      "budam": "별정A",
      "calPrizeY": "0",
      "calPrize_6m": "0",
      "chaksun1": "16500000",
      "chaksun2": "6600000",
      "chaksun3": "4200000",
      "chaksun4": "1500000",
      "chaksun5": "1200000",
      "chaksunT": "0",
      "enNo": "243",
      "hrName": "퀵러너",
      "hrNo": "0052793",
      "meet": "서울",
      "name": "한국",
      "owName": "손병철",
      "owNo": "110058",
      "pgDate": "20260530",
      "pgNo": "2",
      "prdName": "유상호",
      "prizeCond": "R0~0",
      "rank": "국6등급",
      "rcCntY": "5",
      "rcDist": "1300",
      "rcName": "일반",
      "sex": "암",
      "trName": "조현수",
      "trNo": "070199",
      "recentRating": "0"
    },
    {
      "age": "4",
      "ageCond": "연령오픈",
      "budam": "별정A",
      "calPrizeY": "0",
      "calPrize_6m": "0",
      "chaksun1": "16500000",
      "chaksun2": "6600000",
      "chaksun3": "4200000",
      "chaksun4": "1500000",
      "chaksun5": "1200000",
      "chaksunT": "1200000",
      "enNo": "251",
      "hrName": "스마트워리어",
      "hrNo": "0050838",
      "meet": "서울",
      "name": "한국",
      "owName": "박정재",
      "owNo": "010801",
      "pgDate": "20260530",
      "pgNo": "2",
      "prdName": "이상영",
      "prizeCond": "R0~0",
      "rank": "국6등급",
      "rcCntY": "14",
      "rcDist": "1300",
      "rcName": "일반",
      "sex": "암",
      "trName": "심승태",
      "trNo": "070166",
      "recentRating": "0"
    },
    {
      "age": "3",
      "ageCond": "연령오픈",
      "budam": "별정A",
      "calPrizeY": "7800000",
      "calPrize_6m": "7800000",
      "chaksun1": "16500000",
      "chaksun2": "6600000",
      "chaksun3": "4200000",
      "chaksun4": "1500000",
      "chaksun5": "1200000",
      "chaksunT": "12000000",
      "enNo": "255",
      "hrName": "제주블루",
      "hrNo": "0053658",
      "meet": "서울",
      "name": "한국",
      "owName": "미즈타니 마사테루",
      "owNo": "214706",
      "pgDate": "20260530",
      "pgNo": "2",
      "prdName": "최종복",
      "prizeCond": "R0~0",
      "rank": "국6등급",
      "rcCntY": "4",
      "rcDist": "1300",
      "rcName": "일반",
      "sex": "암",
      "trName": "우창구",
      "trNo": "070149",
      "recentRating": "0"
    },
    {
      "age": "3",
      "ageCond": "연령오픈",
      "budam": "별정A",
      "calPrizeY": "0",
      "calPrize_6m": "0",
      "chaksun1": "16500000",
      "chaksun2": "6600000",
      "chaksun3": "4200000",
      "chaksun4": "1500000",
      "chaksun5": "1200000",
      "chaksunT": "0",
      "enNo": "265",
      "hrName": "세명하이디",
      "hrNo": "0054133",
      "meet": "서울",
      "name": "한국",
      "owName": "이기철",
      "owNo": "111051",
      "pgDate": "20260530",
      "pgNo": "2",
      "prdName": "권용찬",
      "prizeCond": "R0~0",
      "rank": "국6등급",
      "rcCntY": "5",
      "rcDist": "1300",
      "rcName": "일반",
      "sex": "암",
      "trName": "홍대유",
      "trNo": "070145",
      "recentRating": "0"
    },
    {
      "age": "4",
      "ageCond": "연령오픈",
      "budam": "별정A",
      "calPrizeY": "10800000",
      "calPrize_6m": "1200000",
      "chaksun1": "16500000",
      "chaksun2": "6600000",
      "chaksun3": "4200000",
      "chaksun4": "1500000",
      "chaksun5": "1200000",
      "chaksunT": "19500000",
      "enNo": "7",
      "hrName": "블루드래곤",
      "hrNo": "0051202",
      "meet": "서울",
      "name": "한국",
      "owName": "이동좌",
      "owNo": "106080",
      "pgDate": "20260530",
      "pgNo": "3",
      "prdName": "신상섭",
      "prizeCond": "R0~0",
      "rank": "국6등급",
      "rcCntY": "8",
      "rcDist": "1700",
      "rcName": "일반",
      "sex": "거",
      "trName": "이관호",
      "trNo": "070181",
      "recentRating": "0"
    },
    {
      "age": "3",
      "ageCond": "연령오픈",
      "budam": "별정A",
      "calPrizeY": "0",
      "calPrize_6m": "0",
      "chaksun1": "16500000",
      "chaksun2": "6600000",
      "chaksun3": "4200000",
      "chaksun4": "1500000",
      "chaksun5": "1200000",
      "chaksunT": "0",
      "enNo": "23",
      "hrName": "송당질주",
      "hrNo": "0053355",
      "meet": "서울",
      "name": "한국",
      "owName": "제주축산개발",
      "owNo": "030013",
      "pgDate": "20260530",
      "pgNo": "3",
      "prdName": "제주축산개발",
      "prizeCond": "R0~0",
      "rank": "국6등급",
      "rcCntY": "3",
      "rcDist": "1700",
      "rcName": "일반",
      "sex": "암",
      "trName": "심승태",
      "trNo": "070166",
      "recentRating": "0"
    },
    {
      "age": "3",
      "ageCond": "연령오픈",
      "budam": "별정A",
      "calPrizeY": "0",
      "calPrize_6m": "0",
      "chaksun1": "16500000",
      "chaksun2": "6600000",
      "chaksun3": "4200000",
      "chaksun4": "1500000",
      "chaksun5": "1200000",
      "chaksunT": "0",
      "enNo": "33",
      "hrName": "브리도칸",
      "hrNo": "0053000",
      "meet": "서울",
      "name": "한국",
      "owName": "조수영",
      "owNo": "122019",
      "pgDate": "20260530",
      "pgNo": "3",
      "prdName": "김태형",
      "prizeCond": "R0~0",
      "rank": "국6등급",
      "rcCntY": "2",
      "rcDist": "1700",
      "rcName": "일반",
      "sex": "거",
      "trName": "정하백",
      "trNo": "070293",
      "recentRating": "0"
    },
    {
      "age": "3",
      "ageCond": "연령오픈",
      "budam": "별정A",
      "calPrizeY": "0",
      "calPrize_6m": "0",
      "chaksun1": "16500000",
      "chaksun2": "6600000",
      "chaksun3": "4200000",
      "chaksun4": "1500000",
      "chaksun5": "1200000",
      "chaksunT": "0",
      "enNo": "91",
      "hrName": "누리퀸즈",
      "hrNo": "0054421",
      "meet": "서울",
      "name": "한국",
      "owName": "허도행",
      "owNo": "104127",
      "pgDate": "20260530",
      "pgNo": "3",
      "prdName": "벽상영농조합법인",
      "prizeCond": "R0~0",
      "rank": "국6등급",
      "rcCntY": "5",
      "rcDist": "1700",
      "rcName": "일반",
      "sex": "암",
      "trName": "성상현",
      "trNo": "070289",
      "recentRating": "0"
    },
    {
      "age": "3",
      "ageCond": "연령오픈",
      "budam": "별정A",
      "calPrizeY": "0",
      "calPrize_6m": "0",
      "chaksun1": "16500000",
      "chaksun2": "6600000",
      "chaksun3": "4200000",
      "chaksun4": "1500000",
      "chaksun5": "1200000",
      "chaksunT": "0",
      "enNo": "97",
      "hrName": "브라운잭팟",
      "hrNo": "0052972",
      "meet": "서울",
      "name": "한국",
      "owName": "이강운",
      "owNo": "121047",
      "pgDate": "20260530",
      "pgNo": "3",
      "prdName": "고성남",
      "prizeCond": "R0~0",
      "rank": "국6등급",
      "rcCntY": "4",
      "rcDist": "1700",
      "rcName": "일반",
      "sex": "암",
      "trName": "강성오",
      "trNo": "070174",
      "recentRating": "0"
    },
    {
      "age": "4",
      "ageCond": "연령오픈",
      "budam": "별정A",
      "calPrizeY": "6900000",
      "calPrize_6m": "5400000",
      "chaksun1": "16500000",
      "chaksun2": "6600000",
      "chaksun3": "4200000",
      "chaksun4": "1500000",
      "chaksun5": "1200000",
      "chaksunT": "8400000",
      "enNo": "98",
      "hrName": "원더풀다르샨",
      "hrNo": "0050760",
      "meet": "서울",
      "name": "한국",
      "owName": "지성배",
      "owNo": "111077",
      "pgDate": "20260530",
      "pgNo": "3",
      "prdName": "(주)녹원목장",
      "prizeCond": "R0~0",
      "rank": "국6등급",
      "rcCntY": "8",
      "rcDist": "1700",
      "rcName": "일반",
      "sex": "수",
      "trName": "강성오",
      "trNo": "070174",
      "recentRating": "0"
    },
    {
      "age": "3",
      "ageCond": "연령오픈",
      "budam": "별정A",
      "calPrizeY": "10500000",
      "calPrize_6m": "7800000",
      "chaksun1": "16500000",
      "chaksun2": "6600000",
      "chaksun3": "4200000",
      "chaksun4": "1500000",
      "chaksun5": "1200000",
      "chaksunT": "27000000",
      "enNo": "121",
      "hrName": "벌교알라딘",
      "hrNo": "0054199",
      "meet": "서울",
      "name": "한국",
      "owName": "유성훈",
      "owNo": "123007",
      "pgDate": "20260530",
      "pgNo": "3",
      "prdName": "김명식",
      "prizeCond": "R0~0",
      "rank": "국6등급",
      "rcCntY": "8",
      "rcDist": "1700",
      "rcName": "일반",
      "sex": "거",
      "trName": "서홍수",
      "trNo": "070160",
      "recentRating": "0"
    },
    {
      "age": "4",
      "ageCond": "연령오픈",
      "budam": "별정A",
      "calPrizeY": "5550000",
      "calPrize_6m": "4050000",
      "chaksun1": "16500000",
      "chaksun2": "6600000",
      "chaksun3": "4200000",
      "chaksun4": "1500000",
      "chaksun5": "1200000",
      "chaksunT": "11250000",
      "enNo": "153",
      "hrName": "원더풀캐시",
      "hrNo": "0051309",
      "meet": "서울",
      "name": "한국",
      "owName": "지대섭",
      "owNo": "010498",
      "pgDate": "20260530",
      "pgNo": "3",
      "prdName": "(주)녹원목장",
      "prizeCond": "R0~0",
      "rank": "국6등급",
      "rcCntY": "8",
      "rcDist": "1700",
      "rcName": "일반",
      "sex": "암",
      "trName": "서범석",
      "trNo": "070096",
      "recentRating": "0"
    },
    {
      "age": "3",
      "ageCond": "연령오픈",
      "budam": "별정A",
      "calPrizeY": "0",
      "calPrize_6m": "0",
      "chaksun1": "16500000",
      "chaksun2": "6600000",
      "chaksun3": "4200000",
      "chaksun4": "1500000",
      "chaksun5": "1200000",
      "chaksunT": "1200000",
      "enNo": "154",
      "hrName": "클럽맨",
      "hrNo": "0053875",
      "meet": "서울",
      "name": "한국",
      "owName": "최홍일",
      "owNo": "110016",
      "pgDate": "20260530",
      "pgNo": "3",
      "prdName": "우림영농조합법인",
      "prizeCond": "R0~0",
      "rank": "국6등급",
      "rcCntY": "5",
      "rcDist": "1700",
      "rcName": "일반",
      "sex": "수",
      "trName": "서범석",
      "trNo": "070096",
      "recentRating": "0"
    },
    {
      "age": "4",
      "ageCond": "연령오픈",
      "budam": "별정A",
      "calPrizeY": "0",
      "calPrize_6m": "0",
      "chaksun1": "16500000",
      "chaksun2": "6600000",
      "chaksun3": "4200000",
      "chaksun4": "1500000",
      "chaksun5": "1200000",
      "chaksunT": "1200000",
      "enNo": "227",
      "hrName": "몬탁선샤인",
      "hrNo": "0050962",
      "meet": "서울",
      "name": "한국",
      "owName": "조금제",
      "owNo": "109017",
      "pgDate": "20260530",
      "pgNo": "3",
      "prdName": "전영환",
      "prizeCond": "R0~0",
      "rank": "국6등급",
      "rcCntY": "16",
      "rcDist": "1700",
      "rcName": "일반",
      "sex": "암",
      "trName": "임채덕",
      "trNo": "070198",
      "recentRating": "0"
    },
    {
      "age": "5",
      "ageCond": "연령오픈",
      "budam": "별정A",
      "calPrizeY": "0",
      "calPrize_6m": "0",
      "chaksun1": "16500000",
      "chaksun2": "6600000",
      "chaksun3": "4200000",
      "chaksun4": "1500000",
      "chaksun5": "1200000",
      "chaksunT": "5400000",
      "enNo": "242",
      "hrName": "질주천하",
      "hrNo": "0046894",
      "meet": "서울",
      "name": "한국",
      "owName": "제일사료(주)",
      "owNo": "105270",
      "pgDate": "20260530",
      "pgNo": "3",
      "prdName": "농업회사법인 주식회사 연학",
      "prizeCond": "R0~0",
      "rank": "국6등급",
      "rcCntY": "11",
      "rcDist": "1700",
      "rcName": "일반",
      "sex": "암",
      "trName": "신삼영",
      "trNo": "070161",
      "recentRating": "0"
    },
    {
      "age": "3",
      "ageCond": "연령오픈",
      "budam": "핸디캡",
      "calPrizeY": "18750000",
      "calPrize_6m": "2250000",
      "chaksun1": "24750000",
      "chaksun2": "9900000",
      "chaksun3": "6300000",
      "chaksun4": "2250000",
      "chaksun5": "1800000",
      "chaksunT": "18750000",
      "enNo": "18",
      "hrName": "나르샤노바",
      "hrNo": "0053406",
      "meet": "서울",
      "name": "한국",
      "owName": "(주)아진화학",
      "owNo": "125010",
      "pgDate": "20260530",
      "pgNo": "4",
      "prdName": "현태봉",
      "prizeCond": "R1~35",
      "rank": "국5등급",
      "rcCntY": "7",
      "rcDist": "1200",
      "rcName": "일반",
      "sex": "암",
      "trName": "정호익",
      "trNo": "070148",
      "recentRating": "28"
    },
    {
      "age": "3",
      "ageCond": "연령오픈",
      "budam": "핸디캡",
      "calPrizeY": "18000000",
      "calPrize_6m": "18000000",
      "chaksun1": "24750000",
      "chaksun2": "9900000",
      "chaksun3": "6300000",
      "chaksun4": "2250000",
      "chaksun5": "1800000",
      "chaksunT": "18000000",
      "enNo": "24",
      "hrName": "오라토리움",
      "hrNo": "0053416",
      "meet": "서울",
      "name": "한국",
      "owName": "오종환",
      "owNo": "065154",
      "pgDate": "20260530",
      "pgNo": "4",
      "prdName": "농업회사법인주식회사케이팜",
      "prizeCond": "R1~35",
      "rank": "국5등급",
      "rcCntY": "2",
      "rcDist": "1200",
      "rcName": "일반",
      "sex": "암",
      "trName": "심승태",
      "trNo": "070166",
      "recentRating": "29"
    },
    {
      "age": "5",
      "ageCond": "연령오픈",
      "budam": "핸디캡",
      "calPrizeY": "10800000",
      "calPrize_6m": "2250000",
      "chaksun1": "24750000",
      "chaksun2": "9900000",
      "chaksun3": "6300000",
      "chaksun4": "2250000",
      "chaksun5": "1800000",
      "chaksunT": "88800000",
      "enNo": "40",
      "hrName": "주링스카이",
      "hrNo": "0047071",
      "meet": "서울",
      "name": "한국",
      "owName": "최임규",
      "owNo": "113032",
      "pgDate": "20260530",
      "pgNo": "4",
      "prdName": "조천근",
      "prizeCond": "R1~35",
      "rank": "국5등급",
      "rcCntY": "15",
      "rcDist": "1200",
      "rcName": "일반",
      "sex": "암",
      "trName": "김동균",
      "trNo": "070170",
      "recentRating": "30"
    },
    {
      "age": "4",
      "ageCond": "연령오픈",
      "budam": "핸디캡",
      "calPrizeY": "26400000",
      "calPrize_6m": "0",
      "chaksun1": "24750000",
      "chaksun2": "9900000",
      "chaksun3": "6300000",
      "chaksun4": "2250000",
      "chaksun5": "1800000",
      "chaksunT": "33000000",
      "enNo": "57",
      "hrName": "미라클삭스",
      "hrNo": "0051403",
      "meet": "서울",
      "name": "한국",
      "owName": "김창식",
      "owNo": "010352",
      "pgDate": "20260530",
      "pgNo": "4",
      "prdName": "김창만",
      "prizeCond": "R1~35",
      "rank": "국5등급",
      "rcCntY": "7",
      "rcDist": "1200",
      "rcName": "일반",
      "sex": "암",
      "trName": "이신우",
      "trNo": "070167",
      "recentRating": "32"
    },
    {
      "age": "4",
      "ageCond": "연령오픈",
      "budam": "핸디캡",
      "calPrizeY": "6300000",
      "calPrize_6m": "6300000",
      "chaksun1": "24750000",
      "chaksun2": "9900000",
      "chaksun3": "6300000",
      "chaksun4": "2250000",
      "chaksun5": "1800000",
      "chaksunT": "35400000",
      "enNo": "92",
      "hrName": "블랙러시안",
      "hrNo": "0051036",
      "meet": "서울",
      "name": "한국",
      "owName": "박재용",
      "owNo": "123005",
      "pgDate": "20260530",
      "pgNo": "4",
      "prdName": "이광림",
      "prizeCond": "R1~35",
      "rank": "국5등급",
      "rcCntY": "12",
      "rcDist": "1200",
      "rcName": "일반",
      "sex": "거",
      "trName": "성상현",
      "trNo": "070289",
      "recentRating": "24"
    },
    {
      "age": "4",
      "ageCond": "연령오픈",
      "budam": "핸디캡",
      "calPrizeY": "2250000",
      "calPrize_6m": "2250000",
      "chaksun1": "24750000",
      "chaksun2": "9900000",
      "chaksun3": "6300000",
      "chaksun4": "2250000",
      "chaksun5": "1800000",
      "chaksunT": "22500000",
      "enNo": "135",
      "hrName": "예스엔젤",
      "hrNo": "0050780",
      "meet": "서울",
      "name": "한국",
      "owName": "조창규",
      "owNo": "065096",
      "pgDate": "20260530",
      "pgNo": "4",
      "prdName": "조창규",
      "prizeCond": "R1~35",
      "rank": "국5등급",
      "rcCntY": "6",
      "rcDist": "1200",
      "rcName": "일반",
      "sex": "암",
      "trName": "박재우",
      "trNo": "070164",
      "recentRating": "25"
    },
    {
      "age": "3",
      "ageCond": "연령오픈",
      "budam": "핸디캡",
      "calPrizeY": "16500000",
      "calPrize_6m": "16500000",
      "chaksun1": "24750000",
      "chaksun2": "9900000",
      "chaksun3": "6300000",
      "chaksun4": "2250000",
      "chaksun5": "1800000",
      "chaksunT": "41250000",
      "enNo": "141",
      "hrName": "래피드선더",
      "hrNo": "0054523",
      "meet": "서울",
      "name": "한국",
      "owName": "이웅열",
      "owNo": "010413",
      "pgDate": "20260530",
      "pgNo": "4",
      "prdName": "김정철",
      "prizeCond": "R1~35",
      "rank": "국5등급",
      "rcCntY": "4",
      "rcDist": "1200",
      "rcName": "일반",
      "sex": "암",
      "trName": "박종곤",
      "trNo": "070095",
      "recentRating": "28"
    },
    {
      "age": "4",
      "ageCond": "연령오픈",
      "budam": "핸디캡",
      "calPrizeY": "31050000",
      "calPrize_6m": "24750000",
      "chaksun1": "24750000",
      "chaksun2": "9900000",
      "chaksun3": "6300000",
      "chaksun4": "2250000",
      "chaksun5": "1800000",
      "chaksunT": "59400000",
      "enNo": "168",
      "hrName": "관악산체크인",
      "hrNo": "0051622",
      "meet": "서울",
      "name": "한국",
      "owName": "손병석",
      "owNo": "123009",
      "pgDate": "20260530",
      "pgNo": "4",
      "prdName": "송용만",
      "prizeCond": "R1~35",
      "rank": "국5등급",
      "rcCntY": "9",
      "rcDist": "1200",
      "rcName": "일반",
      "sex": "거",
      "trName": "이준철",
      "trNo": "070197",
      "recentRating": "35"
    },
    {
      "age": "3",
      "ageCond": "연령오픈",
      "budam": "핸디캡",
      "calPrizeY": "16500000",
      "calPrize_6m": "16500000",
      "chaksun1": "24750000",
      "chaksun2": "9900000",
      "chaksun3": "6300000",
      "chaksun4": "2250000",
      "chaksun5": "1800000",
      "chaksunT": "18300000",
      "enNo": "185",
      "hrName": "아모스스타",
      "hrNo": "0053222",
      "meet": "서울",
      "name": "한국",
      "owName": "홍애란",
      "owNo": "124009",
      "pgDate": "20260530",
      "pgNo": "4",
      "prdName": "김태형",
      "prizeCond": "R1~35",
      "rank": "국5등급",
      "rcCntY": "8",
      "rcDist": "1200",
      "rcName": "일반",
      "sex": "수",
      "trName": "최용건",
      "trNo": "070200",
      "recentRating": "29"
    },
    {
      "age": "4",
      "ageCond": "연령오픈",
      "budam": "핸디캡",
      "calPrizeY": "24900000",
      "calPrize_6m": "20700000",
      "chaksun1": "24750000",
      "chaksun2": "9900000",
      "chaksun3": "6300000",
      "chaksun4": "2250000",
      "chaksun5": "1800000",
      "chaksunT": "24900000",
      "enNo": "208",
      "hrName": "피엔에스공자",
      "hrNo": "0051156",
      "meet": "서울",
      "name": "한국",
      "owName": "피엔에스커튼월",
      "owNo": "118008",
      "pgDate": "20260530",
      "pgNo": "4",
      "prdName": "농업회사법인주식회사피엔에스팜",
      "prizeCond": "R1~35",
      "rank": "국5등급",
      "rcCntY": "7",
      "rcDist": "1200",
      "rcName": "일반",
      "sex": "수",
      "trName": "박윤규",
      "trNo": "070117",
      "recentRating": "29"
    },
    {
      "age": "3",
      "ageCond": "연령오픈",
      "budam": "핸디캡",
      "calPrizeY": "16500000",
      "calPrize_6m": "16500000",
      "chaksun1": "24750000",
      "chaksun2": "9900000",
      "chaksun3": "6300000",
      "chaksun4": "2250000",
      "chaksun5": "1800000",
      "chaksunT": "16500000",
      "enNo": "212",
      "hrName": "비케이데블",
      "hrNo": "0054465",
      "meet": "서울",
      "name": "한국",
      "owName": "함승원",
      "owNo": "109142",
      "pgDate": "20260530",
      "pgNo": "4",
      "prdName": "정환",
      "prizeCond": "R1~35",
      "rank": "국5등급",
      "rcCntY": "7",
      "rcDist": "1200",
      "rcName": "일반",
      "sex": "암",
      "trName": "조현수",
      "trNo": "070199",
      "recentRating": "29"
    },
    {
      "age": "3",
      "ageCond": "연령오픈",
      "budam": "핸디캡",
      "calPrizeY": "24450000",
      "calPrize_6m": "20700000",
      "chaksun1": "24750000",
      "chaksun2": "9900000",
      "chaksun3": "6300000",
      "chaksun4": "2250000",
      "chaksun5": "1800000",
      "chaksunT": "24450000",
      "enNo": "19",
      "hrName": "케렌시아",
      "hrNo": "0053350",
      "meet": "서울",
      "name": "한국",
      "owName": "김경민",
      "owNo": "010542",
      "pgDate": "20260530",
      "pgNo": "5",
      "prdName": "김홍대",
      "prizeCond": "R1~35",
      "rank": "국5등급",
      "rcCntY": "9",
      "rcDist": "1300",
      "rcName": "일반",
      "sex": "수",
      "trName": "정호익",
      "trNo": "070148",
      "recentRating": "28"
    },
    {
      "age": "4",
      "ageCond": "연령오픈",
      "budam": "핸디캡",
      "calPrizeY": "12000000",
      "calPrize_6m": "6300000",
      "chaksun1": "24750000",
      "chaksun2": "9900000",
      "chaksun3": "6300000",
      "chaksun4": "2250000",
      "chaksun5": "1800000",
      "chaksunT": "24150000",
      "enNo": "46",
      "hrName": "천지레이디",
      "hrNo": "0051100",
      "meet": "서울",
      "name": "한국",
      "owName": "김영근",
      "owNo": "112007",
      "pgDate": "20260530",
      "pgNo": "5",
      "prdName": "조천근",
      "prizeCond": "R1~35",
      "rank": "국5등급",
      "rcCntY": "8",
      "rcDist": "1300",
      "rcName": "일반",
      "sex": "암",
      "trName": "김동균",
      "trNo": "070170",
      "recentRating": "26"
    },
    {
      "age": "4",
      "ageCond": "연령오픈",
      "budam": "핸디캡",
      "calPrizeY": "38400000",
      "calPrize_6m": "16200000",
      "chaksun1": "24750000",
      "chaksun2": "9900000",
      "chaksun3": "6300000",
      "chaksun4": "2250000",
      "chaksun5": "1800000",
      "chaksunT": "42450000",
      "enNo": "133",
      "hrName": "초월마",
      "hrNo": "0051265",
      "meet": "서울",
      "name": "한국",
      "owName": "(주)디알엠씨티",
      "owNo": "114026",
      "pgDate": "20260530",
      "pgNo": "5",
      "prdName": "가온영농조합법인",
      "prizeCond": "R1~35",
      "rank": "국5등급",
      "rcCntY": "8",
      "rcDist": "1300",
      "rcName": "일반",
      "sex": "거",
      "trName": "문병기",
      "trNo": "070225",
      "recentRating": "32"
    },
    {
      "age": "5",
      "ageCond": "연령오픈",
      "budam": "핸디캡",
      "calPrizeY": "5400000",
      "calPrize_6m": "2400000",
      "chaksun1": "24750000",
      "chaksun2": "9900000",
      "chaksun3": "6300000",
      "chaksun4": "2250000",
      "chaksun5": "1800000",
      "chaksunT": "112700000",
      "enNo": "162",
      "hrName": "골드베르크",
      "hrNo": "0047186",
      "meet": "서울",
      "name": "한국",
      "owName": "이정화",
      "owNo": "122016",
      "pgDate": "20260530",
      "pgNo": "5",
      "prdName": "오용운",
      "prizeCond": "R1~35",
      "rank": "국5등급",
      "rcCntY": "10",
      "rcDist": "1300",
      "rcName": "일반",
      "sex": "암",
      "trName": "송문길",
      "trNo": "070179",
      "recentRating": "34"
    },
    {
      "age": "3",
      "ageCond": "연령오픈",
      "budam": "핸디캡",
      "calPrizeY": "20700000",
      "calPrize_6m": "8400000",
      "chaksun1": "24750000",
      "chaksun2": "9900000",
      "chaksun3": "6300000",
      "chaksun4": "2250000",
      "chaksun5": "1800000",
      "chaksunT": "30600000",
      "enNo": "189",
      "hrName": "은빛유혹",
      "hrNo": "0054056",
      "meet": "서울",
      "name": "한국",
      "owName": "이종욱",
      "owNo": "065133",
      "pgDate": "20260530",
      "pgNo": "5",
      "prdName": "이종욱",
      "prizeCond": "R1~35",
      "rank": "국5등급",
      "rcCntY": "8",
      "rcDist": "1300",
      "rcName": "일반",
      "sex": "암",
      "trName": "심승태",
      "trNo": "070166",
      "recentRating": "28"
    },
    {
      "age": "6",
      "ageCond": "연령오픈",
      "budam": "핸디캡",
      "calPrizeY": "1800000",
      "calPrize_6m": "0",
      "chaksun1": "24750000",
      "chaksun2": "9900000",
      "chaksun3": "6300000",
      "chaksun4": "2250000",
      "chaksun5": "1800000",
      "chaksunT": "18800000",
      "enNo": "209",
      "hrName": "카리즈마",
      "hrNo": "0046118",
      "meet": "서울",
      "name": "한국",
      "owName": "투애니포",
      "owNo": "121063",
      "pgDate": "20260530",
      "pgNo": "5",
      "prdName": "권용찬",
      "prizeCond": "R1~35",
      "rank": "국5등급",
      "rcCntY": "12",
      "rcDist": "1300",
      "rcName": "일반",
      "sex": "거",
      "trName": "박윤규",
      "trNo": "070117",
      "recentRating": "23"
    },
    {
      "age": "3",
      "ageCond": "연령오픈",
      "budam": "핸디캡",
      "calPrizeY": "43050000",
      "calPrize_6m": "26550000",
      "chaksun1": "24750000",
      "chaksun2": "9900000",
      "chaksun3": "6300000",
      "chaksun4": "2250000",
      "chaksun5": "1800000",
      "chaksunT": "49650000",
      "enNo": "213",
      "hrName": "이십년세월",
      "hrNo": "0053103",
      "meet": "서울",
      "name": "한국",
      "owName": "이혜란",
      "owNo": "104102",
      "pgDate": "20260530",
      "pgNo": "5",
      "prdName": "전영돈",
      "prizeCond": "R1~35",
      "rank": "국5등급",
      "rcCntY": "9",
      "rcDist": "1300",
      "rcName": "일반",
      "sex": "수",
      "trName": "조현수",
      "trNo": "070199",
      "recentRating": "35"
    },
    {
      "age": "3",
      "ageCond": "연령오픈",
      "budam": "핸디캡",
      "calPrizeY": "35850000",
      "calPrize_6m": "35850000",
      "chaksun1": "24750000",
      "chaksun2": "9900000",
      "chaksun3": "6300000",
      "chaksun4": "2250000",
      "chaksun5": "1800000",
      "chaksunT": "35850000",
      "enNo": "217",
      "hrName": "라온더플루마",
      "hrNo": "0053646",
      "meet": "서울",
      "name": "한국",
      "owName": "손천수",
      "owNo": "106025",
      "pgDate": "20260530",
      "pgNo": "5",
      "prdName": "손천수",
      "prizeCond": "R1~35",
      "rank": "국5등급",
      "rcCntY": "5",
      "rcDist": "1300",
      "rcName": "일반",
      "sex": "암",
      "trName": "박종곤",
      "trNo": "070095",
      "recentRating": "30"
    },
    {
      "age": "3",
      "ageCond": "연령오픈",
      "budam": "핸디캡",
      "calPrizeY": "24000000",
      "calPrize_6m": "20700000",
      "chaksun1": "24750000",
      "chaksun2": "9900000",
      "chaksun3": "6300000",
      "chaksun4": "2250000",
      "chaksun5": "1800000",
      "chaksunT": "24000000",
      "enNo": "222",
      "hrName": "파카샤인",
      "hrNo": "0053712",
      "meet": "서울",
      "name": "한국",
      "owName": "디디에스코리아(주)",
      "owNo": "126001",
      "pgDate": "20260530",
      "pgNo": "5",
      "prdName": "김호종",
      "prizeCond": "R1~35",
      "rank": "국5등급",
      "rcCntY": "8",
      "rcDist": "1300",
      "rcName": "일반",
      "sex": "거",
      "trName": "전승규",
      "trNo": "070182",
      "recentRating": "29"
    },
    {
      "age": "4",
      "ageCond": "연령오픈",
      "budam": "핸디캡",
      "calPrizeY": "41250000",
      "calPrize_6m": "0",
      "chaksun1": "24750000",
      "chaksun2": "9900000",
      "chaksun3": "6300000",
      "chaksun4": "2250000",
      "chaksun5": "1800000",
      "chaksunT": "56100000",
      "enNo": "228",
      "hrName": "삼정레이디",
      "hrNo": "0052088",
      "meet": "서울",
      "name": "한국",
      "owName": "김호선",
      "owNo": "113135",
      "pgDate": "20260530",
      "pgNo": "5",
      "prdName": "임정균",
      "prizeCond": "R1~35",
      "rank": "국5등급",
      "rcCntY": "5",
      "rcDist": "1300",
      "rcName": "일반",
      "sex": "암",
      "trName": "강환민",
      "trNo": "070175",
      "recentRating": "34"
    },
    {
      "age": "3",
      "ageCond": "연령오픈",
      "budam": "핸디캡",
      "calPrizeY": "54000000",
      "calPrize_6m": "27000000",
      "chaksun1": "24750000",
      "chaksun2": "9900000",
      "chaksun3": "6300000",
      "chaksun4": "2250000",
      "chaksun5": "1800000",
      "chaksunT": "65700000",
      "enNo": "254",
      "hrName": "랩처",
      "hrNo": "0053633",
      "meet": "서울",
      "name": "한국",
      "owName": "강승연",
      "owNo": "065060",
      "pgDate": "20260530",
      "pgNo": "5",
      "prdName": "양남일",
      "prizeCond": "R1~35",
      "rank": "국5등급",
      "rcCntY": "9",
      "rcDist": "1300",
      "rcName": "일반",
      "sex": "암",
      "trName": "최용구",
      "trNo": "070168",
      "recentRating": "34"
    },
    {
      "age": "4",
      "ageCond": "연령오픈",
      "budam": "핸디캡",
      "calPrizeY": "22800000",
      "calPrize_6m": "0",
      "chaksun1": "24750000",
      "chaksun2": "9900000",
      "chaksun3": "6300000",
      "chaksun4": "2250000",
      "chaksun5": "1800000",
      "chaksunT": "22800000",
      "enNo": "268",
      "hrName": "선더파이어",
      "hrNo": "0050852",
      "meet": "서울",
      "name": "한국",
      "owName": "변갑한",
      "owNo": "109014",
      "pgDate": "20260530",
      "pgNo": "5",
      "prdName": "배은정",
      "prizeCond": "R1~35",
      "rank": "국5등급",
      "rcCntY": "4",
      "rcDist": "1300",
      "rcName": "일반",
      "sex": "거",
      "trName": "함완식",
      "trNo": "070248",
      "recentRating": "28"
    },
    {
      "age": "6",
      "ageCond": "연령오픈",
      "budam": "핸디캡",
      "calPrizeY": "22050000",
      "calPrize_6m": "12150000",
      "chaksun1": "24750000",
      "chaksun2": "9900000",
      "chaksun3": "6300000",
      "chaksun4": "2250000",
      "chaksun5": "1800000",
      "chaksunT": "100750000",
      "enNo": "6",
      "hrName": "파이널질주",
      "hrNo": "0045610",
      "meet": "서울",
      "name": "한국",
      "owName": "럭키",
      "owNo": "124010",
      "pgDate": "20260530",
      "pgNo": "6",
      "prdName": "이상영",
      "prizeCond": "R1~35",
      "rank": "국5등급",
      "rcCntY": "13",
      "rcDist": "1400",
      "rcName": "일반",
      "sex": "암",
      "trName": "임채덕",
      "trNo": "070198",
      "recentRating": "35"
    },
    {
      "age": "4",
      "ageCond": "연령오픈",
      "budam": "핸디캡",
      "calPrizeY": "24300000",
      "calPrize_6m": "18000000",
      "chaksun1": "24750000",
      "chaksun2": "9900000",
      "chaksun3": "6300000",
      "chaksun4": "2250000",
      "chaksun5": "1800000",
      "chaksunT": "63600000",
      "enNo": "51",
      "hrName": "두레이쇼",
      "hrNo": "0051649",
      "meet": "서울",
      "name": "한국",
      "owName": "김영근",
      "owNo": "112007",
      "pgDate": "20260530",
      "pgNo": "6",
      "prdName": "조천근",
      "prizeCond": "R1~35",
      "rank": "국5등급",
      "rcCntY": "14",
      "rcDist": "1400",
      "rcName": "일반",
      "sex": "암",
      "trName": "김동균",
      "trNo": "070170",
      "recentRating": "32"
    },
    {
      "age": "4",
      "ageCond": "연령오픈",
      "budam": "핸디캡",
      "calPrizeY": "27300000",
      "calPrize_6m": "16500000",
      "chaksun1": "24750000",
      "chaksun2": "9900000",
      "chaksun3": "6300000",
      "chaksun4": "2250000",
      "chaksun5": "1800000",
      "chaksunT": "30600000",
      "enNo": "93",
      "hrName": "키아오라",
      "hrNo": "0052051",
      "meet": "서울",
      "name": "한국",
      "owName": "박재용",
      "owNo": "123005",
      "pgDate": "20260530",
      "pgNo": "6",
      "prdName": "제주축산개발",
      "prizeCond": "R1~35",
      "rank": "국5등급",
      "rcCntY": "6",
      "rcDist": "1400",
      "rcName": "일반",
      "sex": "암",
      "trName": "성상현",
      "trNo": "070289",
      "recentRating": "28"
    },
    {
      "age": "5",
      "ageCond": "연령오픈",
      "budam": "핸디캡",
      "calPrizeY": "8250000",
      "calPrize_6m": "1800000",
      "chaksun1": "24750000",
      "chaksun2": "9900000",
      "chaksun3": "6300000",
      "chaksun4": "2250000",
      "chaksun5": "1800000",
      "chaksunT": "21750000",
      "enNo": "119",
      "hrName": "혜원용마",
      "hrNo": "0047255",
      "meet": "서울",
      "name": "한국",
      "owName": "이혜섭",
      "owNo": "123010",
      "pgDate": "20260530",
      "pgNo": "6",
      "prdName": "윤흥열",
      "prizeCond": "R1~35",
      "rank": "국5등급",
      "rcCntY": "8",
      "rcDist": "1400",
      "rcName": "일반",
      "sex": "암",
      "trName": "서인석",
      "trNo": "070165",
      "recentRating": "23"
    },
    {
      "age": "4",
      "ageCond": "연령오픈",
      "budam": "핸디캡",
      "calPrizeY": "23700000",
      "calPrize_6m": "18000000",
      "chaksun1": "24750000",
      "chaksun2": "9900000",
      "chaksun3": "6300000",
      "chaksun4": "2250000",
      "chaksun5": "1800000",
      "chaksunT": "26700000",
      "enNo": "152",
      "hrName": "대한코코즈",
      "hrNo": "0050809",
      "meet": "서울",
      "name": "한국",
      "owName": "이종수",
      "owNo": "124012",
      "pgDate": "20260530",
      "pgNo": "6",
      "prdName": "배은정",
      "prizeCond": "R1~35",
      "rank": "국5등급",
      "rcCntY": "9",
      "rcDist": "1400",
      "rcName": "일반",
      "sex": "암",
      "trName": "강성오",
      "trNo": "070174",
      "recentRating": "28"
    },
    {
      "age": "4",
      "ageCond": "연령오픈",
      "budam": "핸디캡",
      "calPrizeY": "8100000",
      "calPrize_6m": "4050000",
      "chaksun1": "24750000",
      "chaksun2": "9900000",
      "chaksun3": "6300000",
      "chaksun4": "2250000",
      "chaksun5": "1800000",
      "chaksunT": "48900000",
      "enNo": "233",
      "hrName": "큐피드케이",
      "hrNo": "0050957",
      "meet": "서울",
      "name": "한국",
      "owName": "강경운",
      "owNo": "117025",
      "pgDate": "20260530",
      "pgNo": "6",
      "prdName": "임정균",
      "prizeCond": "R1~35",
      "rank": "국5등급",
      "rcCntY": "11",
      "rcDist": "1400",
      "rcName": "일반",
      "sex": "암",
      "trName": "강환민",
      "trNo": "070175",
      "recentRating": "26"
    },
    {
      "age": "4",
      "ageCond": "연령오픈",
      "budam": "핸디캡",
      "calPrizeY": "3000000",
      "calPrize_6m": "0",
      "chaksun1": "24750000",
      "chaksun2": "9900000",
      "chaksun3": "6300000",
      "chaksun4": "2250000",
      "chaksun5": "1800000",
      "chaksunT": "93050000",
      "enNo": "240",
      "hrName": "걸작시대",
      "hrNo": "0050858",
      "meet": "서울",
      "name": "한국",
      "owName": "박덕희",
      "owNo": "105249",
      "pgDate": "20260530",
      "pgNo": "6",
      "prdName": "최장석",
      "prizeCond": "R1~35",
      "rank": "국5등급",
      "rcCntY": "8",
      "rcDist": "1400",
      "rcName": "일반",
      "sex": "암",
      "trName": "박윤규",
      "trNo": "070117",
      "recentRating": "33"
    },
    {
      "age": "3",
      "ageCond": "연령오픈",
      "budam": "핸디캡",
      "calPrizeY": "27000000",
      "calPrize_6m": "27000000",
      "chaksun1": "24750000",
      "chaksun2": "9900000",
      "chaksun3": "6300000",
      "chaksun4": "2250000",
      "chaksun5": "1800000",
      "chaksunT": "29250000",
      "enNo": "246",
      "hrName": "퍼플코리아",
      "hrNo": "0054462",
      "meet": "서울",
      "name": "한국",
      "owName": "퍼플라인",
      "owNo": "121053",
      "pgDate": "20260530",
      "pgNo": "6",
      "prdName": "제주축산개발",
      "prizeCond": "R1~35",
      "rank": "국5등급",
      "rcCntY": "4",
      "rcDist": "1400",
      "rcName": "일반",
      "sex": "암",
      "trName": "최용건",
      "trNo": "070200",
      "recentRating": "29"
    },
    {
      "age": "4",
      "ageCond": "연령오픈",
      "budam": "핸디캡",
      "calPrizeY": "14850000",
      "calPrize_6m": "4050000",
      "chaksun1": "24750000",
      "chaksun2": "9900000",
      "chaksun3": "6300000",
      "chaksun4": "2250000",
      "chaksun5": "1800000",
      "chaksunT": "43650000",
      "enNo": "249",
      "hrName": "기대하라",
      "hrNo": "0051150",
      "meet": "서울",
      "name": "한국",
      "owName": "남석우",
      "owNo": "105055",
      "pgDate": "20260530",
      "pgNo": "6",
      "prdName": "이경우",
      "prizeCond": "R1~35",
      "rank": "국5등급",
      "rcCntY": "10",
      "rcDist": "1400",
      "rcName": "일반",
      "sex": "암",
      "trName": "이관호",
      "trNo": "070181",
      "recentRating": "30"
    },
    {
      "age": "4",
      "ageCond": "연령오픈",
      "budam": "핸디캡",
      "calPrizeY": "12600000",
      "calPrize_6m": "12600000",
      "chaksun1": "24750000",
      "chaksun2": "9900000",
      "chaksun3": "6300000",
      "chaksun4": "2250000",
      "chaksun5": "1800000",
      "chaksunT": "42150000",
      "enNo": "250",
      "hrName": "굿프렌드",
      "hrNo": "0050935",
      "meet": "서울",
      "name": "한국",
      "owName": "말사모",
      "owNo": "116058",
      "pgDate": "20260530",
      "pgNo": "6",
      "prdName": "이병일",
      "prizeCond": "R1~35",
      "rank": "국5등급",
      "rcCntY": "15",
      "rcDist": "1400",
      "rcName": "일반",
      "sex": "암",
      "trName": "안병기",
      "trNo": "070146",
      "recentRating": "24"
    },
    {
      "age": "3",
      "ageCond": "연령오픈",
      "budam": "핸디캡",
      "calPrizeY": "24750000",
      "calPrize_6m": "24750000",
      "chaksun1": "24750000",
      "chaksun2": "9900000",
      "chaksun3": "6300000",
      "chaksun4": "2250000",
      "chaksun5": "1800000",
      "chaksunT": "49500000",
      "enNo": "262",
      "hrName": "더선스토리",
      "hrNo": "0053211",
      "meet": "서울",
      "name": "한국",
      "owName": "한명로",
      "owNo": "111053",
      "pgDate": "20260530",
      "pgNo": "6",
      "prdName": "농업회사법인 주식회사 더선라이즈",
      "prizeCond": "R1~35",
      "rank": "국5등급",
      "rcCntY": "4",
      "rcDist": "1400",
      "rcName": "일반",
      "sex": "암",
      "trName": "홍윤화",
      "trNo": "070306",
      "recentRating": "29"
    },
    {
      "age": "5",
      "ageCond": "연령오픈",
      "budam": "핸디캡",
      "calPrizeY": "0",
      "calPrize_6m": "0",
      "chaksun1": "24750000",
      "chaksun2": "9900000",
      "chaksun3": "6300000",
      "chaksun4": "2250000",
      "chaksun5": "1800000",
      "chaksunT": "30450000",
      "enNo": "263",
      "hrName": "에클레어",
      "hrNo": "0047223",
      "meet": "서울",
      "name": "한국",
      "owName": "제이엘피코퍼레이션",
      "owNo": "124020",
      "pgDate": "20260530",
      "pgNo": "6",
      "prdName": "오공학",
      "prizeCond": "R1~35",
      "rank": "국5등급",
      "rcCntY": "13",
      "rcDist": "1400",
      "rcName": "일반",
      "sex": "암",
      "trName": "서홍수",
      "trNo": "070160",
      "recentRating": "23"
    },
    {
      "age": "7",
      "ageCond": "연령오픈",
      "budam": "핸디캡",
      "calPrizeY": "55500000",
      "calPrize_6m": "10500000",
      "chaksun1": "41250000",
      "chaksun2": "16500000",
      "chaksun3": "10500000",
      "chaksun4": "3750000",
      "chaksun5": "3000000",
      "chaksunT": "312150000",
      "enNo": "8",
      "hrName": "와일드삭스",
      "hrNo": "0044287",
      "meet": "서울",
      "name": "한국",
      "owName": "김창식",
      "owNo": "010352",
      "pgDate": "20260530",
      "pgNo": "7",
      "prdName": "정성빈",
      "prizeCond": "R1~65",
      "rank": "국3등급",
      "rcCntY": "12",
      "rcDist": "1600",
      "rcName": "일반",
      "sex": "수",
      "trName": "이관호",
      "trNo": "070181",
      "recentRating": "57"
    },
    {
      "age": "5",
      "ageCond": "연령오픈",
      "budam": "핸디캡",
      "calPrizeY": "44400000",
      "calPrize_6m": "41400000",
      "chaksun1": "41250000",
      "chaksun2": "16500000",
      "chaksun3": "10500000",
      "chaksun4": "3750000",
      "chaksun5": "3000000",
      "chaksunT": "143200000",
      "enNo": "62",
      "hrName": "매직스트롱",
      "hrNo": "0046641",
      "meet": "서울",
      "name": "한국",
      "owName": "최상기",
      "owNo": "105263",
      "pgDate": "20260530",
      "pgNo": "7",
      "prdName": "최상일",
      "prizeCond": "R1~65",
      "rank": "국3등급",
      "rcCntY": "8",
      "rcDist": "1600",
      "rcName": "일반",
      "sex": "수",
      "trName": "토니",
      "trNo": "070265",
      "recentRating": "56"
    },
    {
      "age": "4",
      "ageCond": "연령오픈",
      "budam": "핸디캡",
      "calPrizeY": "85950000",
      "calPrize_6m": "67650000",
      "chaksun1": "41250000",
      "chaksun2": "16500000",
      "chaksun3": "10500000",
      "chaksun4": "3750000",
      "chaksun5": "3000000",
      "chaksunT": "133800000",
      "enNo": "82",
      "hrName": "마스터콰이곤",
      "hrNo": "0051768",
      "meet": "서울",
      "name": "한국",
      "owName": "이호열",
      "owNo": "121001",
      "pgDate": "20260530",
      "pgNo": "7",
      "prdName": "이경하",
      "prizeCond": "R1~65",
      "rank": "국3등급",
      "rcCntY": "9",
      "rcDist": "1600",
      "rcName": "일반",
      "sex": "수",
      "trName": "리카디",
      "trNo": "070244",
      "recentRating": "51"
    },
    {
      "age": "4",
      "ageCond": "연령오픈",
      "budam": "핸디캡",
      "calPrizeY": "55500000",
      "calPrize_6m": "51750000",
      "chaksun1": "41250000",
      "chaksun2": "16500000",
      "chaksun3": "10500000",
      "chaksun4": "3750000",
      "chaksun5": "3000000",
      "chaksunT": "198950000",
      "enNo": "86",
      "hrName": "한강퍼펙트",
      "hrNo": "0051116",
      "meet": "서울",
      "name": "한국",
      "owName": "조금제",
      "owNo": "109017",
      "pgDate": "20260530",
      "pgNo": "7",
      "prdName": "이승철",
      "prizeCond": "R1~65",
      "rank": "국3등급",
      "rcCntY": "9",
      "rcDist": "1600",
      "rcName": "일반",
      "sex": "수",
      "trName": "배휴준",
      "trNo": "070144",
      "recentRating": "62"
    },
    {
      "age": "4",
      "ageCond": "연령오픈",
      "budam": "핸디캡",
      "calPrizeY": "9750000",
      "calPrize_6m": "6750000",
      "chaksun1": "41250000",
      "chaksun2": "16500000",
      "chaksun3": "10500000",
      "chaksun4": "3750000",
      "chaksun5": "3000000",
      "chaksunT": "429400000",
      "enNo": "123",
      "hrName": "아쿠아라인",
      "hrNo": "0051794",
      "meet": "서울",
      "name": "한국",
      "owName": "미즈타니 마사테루",
      "owNo": "214706",
      "pgDate": "20260530",
      "pgNo": "7",
      "prdName": "최종복",
      "prizeCond": "R1~65",
      "rank": "국3등급",
      "rcCntY": "8",
      "rcDist": "1600",
      "rcName": "일반",
      "sex": "수",
      "trName": "서범석",
      "trNo": "070096",
      "recentRating": "48"
    },
    {
      "age": "5",
      "ageCond": "연령오픈",
      "budam": "핸디캡",
      "calPrizeY": "104700000",
      "calPrize_6m": "48000000",
      "chaksun1": "41250000",
      "chaksun2": "16500000",
      "chaksun3": "10500000",
      "chaksun4": "3750000",
      "chaksun5": "3000000",
      "chaksunT": "202950000",
      "enNo": "124",
      "hrName": "원더풀로드",
      "hrNo": "0047440",
      "meet": "서울",
      "name": "한국",
      "owName": "지대섭",
      "owNo": "010498",
      "pgDate": "20260530",
      "pgNo": "7",
      "prdName": "(주)녹원목장",
      "prizeCond": "R1~65",
      "rank": "국3등급",
      "rcCntY": "8",
      "rcDist": "1600",
      "rcName": "일반",
      "sex": "수",
      "trName": "서인석",
      "trNo": "070165",
      "recentRating": "62"
    },
    {
      "age": "4",
      "ageCond": "연령오픈",
      "budam": "핸디캡",
      "calPrizeY": "66450000",
      "calPrize_6m": "3750000",
      "chaksun1": "41250000",
      "chaksun2": "16500000",
      "chaksun3": "10500000",
      "chaksun4": "3750000",
      "chaksun5": "3000000",
      "chaksunT": "183750000",
      "enNo": "158",
      "hrName": "케이파워풀",
      "hrNo": "0052131",
      "meet": "서울",
      "name": "한국",
      "owName": "최홍일",
      "owNo": "110016",
      "pgDate": "20260530",
      "pgNo": "7",
      "prdName": "우림영농조합법인",
      "prizeCond": "R1~65",
      "rank": "국3등급",
      "rcCntY": "10",
      "rcDist": "1600",
      "rcName": "일반",
      "sex": "수",
      "trName": "서범석",
      "trNo": "070096",
      "recentRating": "57"
    },
    {
      "age": "4",
      "ageCond": "연령오픈",
      "budam": "핸디캡",
      "calPrizeY": "74250000",
      "calPrize_6m": "0",
      "chaksun1": "41250000",
      "chaksun2": "16500000",
      "chaksun3": "10500000",
      "chaksun4": "3750000",
      "chaksun5": "3000000",
      "chaksunT": "178050000",
      "enNo": "186",
      "hrName": "즐거운상상",
      "hrNo": "0051830",
      "meet": "서울",
      "name": "한국",
      "owName": "우태율",
      "owNo": "111006",
      "pgDate": "20260530",
      "pgNo": "7",
      "prdName": "김기석",
      "prizeCond": "R1~65",
      "rank": "국3등급",
      "rcCntY": "11",
      "rcDist": "1600",
      "rcName": "일반",
      "sex": "수",
      "trName": "최용건",
      "trNo": "070200",
      "recentRating": "60"
    },
    {
      "age": "6",
      "ageCond": "연령오픈",
      "budam": "핸디캡",
      "calPrizeY": "31500000",
      "calPrize_6m": "14250000",
      "chaksun1": "41250000",
      "chaksun2": "16500000",
      "chaksun3": "10500000",
      "chaksun4": "3750000",
      "chaksun5": "3000000",
      "chaksunT": "191600000",
      "enNo": "214",
      "hrName": "비전파워",
      "hrNo": "0045934",
      "meet": "서울",
      "name": "한국",
      "owName": "손병현",
      "owNo": "112005",
      "pgDate": "20260530",
      "pgNo": "7",
      "prdName": "손병현",
      "prizeCond": "R1~65",
      "rank": "국3등급",
      "rcCntY": "10",
      "rcDist": "1600",
      "rcName": "일반",
      "sex": "수",
      "trName": "조현수",
      "trNo": "070199",
      "recentRating": "55"
    },
    {
      "age": "4",
      "ageCond": "연령오픈",
      "budam": "핸디캡",
      "calPrizeY": "66000000",
      "calPrize_6m": "33000000",
      "chaksun1": "41250000",
      "chaksun2": "16500000",
      "chaksun3": "10500000",
      "chaksun4": "3750000",
      "chaksun5": "3000000",
      "chaksunT": "151650000",
      "enNo": "226",
      "hrName": "그레이스루트",
      "hrNo": "0051657",
      "meet": "서울",
      "name": "한국",
      "owName": "박남성",
      "owNo": "010496",
      "pgDate": "20260530",
      "pgNo": "7",
      "prdName": "송용만",
      "prizeCond": "R1~65",
      "rank": "국3등급",
      "rcCntY": "12",
      "rcDist": "1600",
      "rcName": "일반",
      "sex": "암",
      "trName": "박재우",
      "trNo": "070164",
      "recentRating": "57"
    },
    {
      "age": "5",
      "ageCond": "연령오픈",
      "budam": "핸디캡",
      "calPrizeY": "45000000",
      "calPrize_6m": "24000000",
      "chaksun1": "41250000",
      "chaksun2": "16500000",
      "chaksun3": "10500000",
      "chaksun4": "3750000",
      "chaksun5": "3000000",
      "chaksunT": "223300000",
      "enNo": "231",
      "hrName": "세광파이터",
      "hrNo": "1412326",
      "meet": "서울",
      "name": "한국",
      "owName": "배형진",
      "owNo": "123014",
      "pgDate": "20260530",
      "pgNo": "7",
      "prdName": "김을분",
      "prizeCond": "R1~65",
      "rank": "국3등급",
      "rcCntY": "9",
      "rcDist": "1600",
      "rcName": "일반",
      "sex": "수",
      "trName": "최용구",
      "trNo": "070168",
      "recentRating": "64"
    },
    {
      "age": "4",
      "ageCond": "연령오픈",
      "budam": "핸디캡",
      "calPrizeY": "39300000",
      "calPrize_6m": "25500000",
      "chaksun1": "33000000",
      "chaksun2": "13200000",
      "chaksun3": "8400000",
      "chaksun4": "3000000",
      "chaksun5": "2400000",
      "chaksunT": "58500000",
      "enNo": "16",
      "hrName": "별콩",
      "hrNo": "0055095",
      "meet": "서울",
      "name": "뉴질랜드",
      "owName": "이태인",
      "owNo": "010316",
      "pgDate": "20260530",
      "pgNo": "8",
      "prdName": "G HARVEY",
      "prizeCond": "R0~50",
      "rank": "혼4등급",
      "rcCntY": "8",
      "rcDist": "1800",
      "rcName": "일반",
      "sex": "거",
      "trName": "서인석",
      "trNo": "070165",
      "recentRating": "44"
    },
    {
      "age": "3",
      "ageCond": "연령오픈",
      "budam": "핸디캡",
      "calPrizeY": "18000000",
      "calPrize_6m": "18000000",
      "chaksun1": "33000000",
      "chaksun2": "13200000",
      "chaksun3": "8400000",
      "chaksun4": "3000000",
      "chaksun5": "2400000",
      "chaksunT": "18000000",
      "enNo": "83",
      "hrName": "하이마운틴",
      "hrNo": "0060828",
      "meet": "서울",
      "name": "미국",
      "owName": "이기선",
      "owNo": "010516",
      "pgDate": "20260530",
      "pgNo": "8",
      "prdName": "Omar Ramirez",
      "prizeCond": "R0~50",
      "rank": "혼4등급",
      "rcCntY": "3",
      "rcDist": "1800",
      "rcName": "일반",
      "sex": "수",
      "trName": "리카디",
      "trNo": "070244",
      "recentRating": "39"
    },
    {
      "age": "3",
      "ageCond": "연령오픈",
      "budam": "핸디캡",
      "calPrizeY": "64650000",
      "calPrize_6m": "37650000",
      "chaksun1": "33000000",
      "chaksun2": "13200000",
      "chaksun3": "8400000",
      "chaksun4": "3000000",
      "chaksun5": "2400000",
      "chaksunT": "97650000",
      "enNo": "134",
      "hrName": "밸리드영",
      "hrNo": "0053760",
      "meet": "서울",
      "name": "한국",
      "owName": "(주)디알엠씨티",
      "owNo": "114026",
      "pgDate": "20260530",
      "pgNo": "8",
      "prdName": "농업회사법인 굿원",
      "prizeCond": "R0~50",
      "rank": "혼4등급",
      "rcCntY": "6",
      "rcDist": "1800",
      "rcName": "일반",
      "sex": "수",
      "trName": "문병기",
      "trNo": "070225",
      "recentRating": "39"
    },
    {
      "age": "5",
      "ageCond": "연령오픈",
      "budam": "핸디캡",
      "calPrizeY": "43800000",
      "calPrize_6m": "10800000",
      "chaksun1": "33000000",
      "chaksun2": "13200000",
      "chaksun3": "8400000",
      "chaksun4": "3000000",
      "chaksun5": "2400000",
      "chaksunT": "110850000",
      "enNo": "146",
      "hrName": "인피니트아너",
      "hrNo": "0047314",
      "meet": "서울",
      "name": "한국",
      "owName": "김중길",
      "owNo": "105057",
      "pgDate": "20260530",
      "pgNo": "8",
      "prdName": "김중길",
      "prizeCond": "R0~50",
      "rank": "혼4등급",
      "rcCntY": "8",
      "rcDist": "1800",
      "rcName": "일반",
      "sex": "거",
      "trName": "강성오",
      "trNo": "070174",
      "recentRating": "44"
    },
    {
      "age": "5",
      "ageCond": "연령오픈",
      "budam": "핸디캡",
      "calPrizeY": "7800000",
      "calPrize_6m": "3000000",
      "chaksun1": "33000000",
      "chaksun2": "13200000",
      "chaksun3": "8400000",
      "chaksun4": "3000000",
      "chaksun5": "2400000",
      "chaksunT": "49500000",
      "enNo": "147",
      "hrName": "빅토리퀸",
      "hrNo": "0052832",
      "meet": "서울",
      "name": "미국",
      "owName": "(주)디알엠씨티",
      "owNo": "114026",
      "pgDate": "20260530",
      "pgNo": "8",
      "prdName": "Kentucky",
      "prizeCond": "R0~50",
      "rank": "혼4등급",
      "rcCntY": "9",
      "rcDist": "1800",
      "rcName": "일반",
      "sex": "암",
      "trName": "강성오",
      "trNo": "070174",
      "recentRating": "39"
    },
    {
      "age": "4",
      "ageCond": "연령오픈",
      "budam": "핸디캡",
      "calPrizeY": "53400000",
      "calPrize_6m": "46200000",
      "chaksun1": "33000000",
      "chaksun2": "13200000",
      "chaksun3": "8400000",
      "chaksun4": "3000000",
      "chaksun5": "2400000",
      "chaksunT": "53400000",
      "enNo": "150",
      "hrName": "마이티프리",
      "hrNo": "0055091",
      "meet": "서울",
      "name": "호주",
      "owName": "조병태",
      "owNo": "113005",
      "pgDate": "20260530",
      "pgNo": "8",
      "prdName": "MUSK CREEK FARM",
      "prizeCond": "R0~50",
      "rank": "혼4등급",
      "rcCntY": "8",
      "rcDist": "1800",
      "rcName": "일반",
      "sex": "거",
      "trName": "함완식",
      "trNo": "070248",
      "recentRating": "46"
    },
    {
      "age": "4",
      "ageCond": "연령오픈",
      "budam": "핸디캡",
      "calPrizeY": "55800000",
      "calPrize_6m": "11400000",
      "chaksun1": "33000000",
      "chaksun2": "13200000",
      "chaksun3": "8400000",
      "chaksun4": "3000000",
      "chaksun5": "2400000",
      "chaksunT": "70800000",
      "enNo": "155",
      "hrName": "축배를들어라",
      "hrNo": "0055384",
      "meet": "서울",
      "name": "호주",
      "owName": "(주)나스카",
      "owNo": "110034",
      "pgDate": "20260530",
      "pgNo": "8",
      "prdName": "-",
      "prizeCond": "R0~50",
      "rank": "혼4등급",
      "rcCntY": "7",
      "rcDist": "1800",
      "rcName": "일반",
      "sex": "거",
      "trName": "송문길",
      "trNo": "070179",
      "recentRating": "46"
    },
    {
      "age": "3",
      "ageCond": "연령오픈",
      "budam": "핸디캡",
      "calPrizeY": "0",
      "calPrize_6m": "0",
      "chaksun1": "33000000",
      "chaksun2": "13200000",
      "chaksun3": "8400000",
      "chaksun4": "3000000",
      "chaksun5": "2400000",
      "chaksunT": "0",
      "enNo": "171",
      "hrName": "선돌풍",
      "hrNo": "0057364",
      "meet": "서울",
      "name": "미국",
      "owName": "(주)선우패션",
      "owNo": "030012",
      "pgDate": "20260530",
      "pgNo": "8",
      "prdName": "Lothenbach Stables Inc",
      "prizeCond": "R0~50",
      "rank": "혼4등급",
      "rcCntY": "3",
      "rcDist": "1800",
      "rcName": "일반",
      "sex": "수",
      "trName": "홍대유",
      "trNo": "070145",
      "recentRating": "36"
    },
    {
      "age": "3",
      "ageCond": "연령오픈",
      "budam": "핸디캡",
      "calPrizeY": "59400000",
      "calPrize_6m": "34650000",
      "chaksun1": "33000000",
      "chaksun2": "13200000",
      "chaksun3": "8400000",
      "chaksun4": "3000000",
      "chaksun5": "2400000",
      "chaksunT": "72600000",
      "enNo": "181",
      "hrName": "다나은스타",
      "hrNo": "0053213",
      "meet": "서울",
      "name": "한국",
      "owName": "이진경",
      "owNo": "117021",
      "pgDate": "20260530",
      "pgNo": "8",
      "prdName": "이경우",
      "prizeCond": "R0~50",
      "rank": "혼4등급",
      "rcCntY": "5",
      "rcDist": "1800",
      "rcName": "일반",
      "sex": "수",
      "trName": "이준철",
      "trNo": "070197",
      "recentRating": "39"
    },
    {
      "age": "4",
      "ageCond": "연령오픈",
      "budam": "핸디캡",
      "calPrizeY": "49050000",
      "calPrize_6m": "37350000",
      "chaksun1": "33000000",
      "chaksun2": "13200000",
      "chaksun3": "8400000",
      "chaksun4": "3000000",
      "chaksun5": "2400000",
      "chaksunT": "79050000",
      "enNo": "198",
      "hrName": "선더마블",
      "hrNo": "0051384",
      "meet": "서울",
      "name": "한국",
      "owName": "변갑한",
      "owNo": "109014",
      "pgDate": "20260530",
      "pgNo": "8",
      "prdName": "배은정",
      "prizeCond": "R0~50",
      "rank": "혼4등급",
      "rcCntY": "10",
      "rcDist": "1800",
      "rcName": "일반",
      "sex": "거",
      "trName": "우창구",
      "trNo": "070149",
      "recentRating": "38"
    },
    {
      "age": "4",
      "ageCond": "연령오픈",
      "budam": "핸디캡",
      "calPrizeY": "13200000",
      "calPrize_6m": "0",
      "chaksun1": "33000000",
      "chaksun2": "13200000",
      "chaksun3": "8400000",
      "chaksun4": "3000000",
      "chaksun5": "2400000",
      "chaksunT": "88200000",
      "enNo": "215",
      "hrName": "불의세계",
      "hrNo": "0051628",
      "meet": "서울",
      "name": "한국",
      "owName": "이혜란",
      "owNo": "104102",
      "pgDate": "20260530",
      "pgNo": "8",
      "prdName": "전영돈",
      "prizeCond": "R0~50",
      "rank": "혼4등급",
      "rcCntY": "11",
      "rcDist": "1800",
      "rcName": "일반",
      "sex": "거",
      "trName": "조현수",
      "trNo": "070199",
      "recentRating": "41"
    },
    {
      "age": "4",
      "ageCond": "연령오픈",
      "budam": "핸디캡",
      "calPrizeY": "13500000",
      "calPrize_6m": "3000000",
      "chaksun1": "33000000",
      "chaksun2": "13200000",
      "chaksun3": "8400000",
      "chaksun4": "3000000",
      "chaksun5": "2400000",
      "chaksunT": "21900000",
      "enNo": "223",
      "hrName": "글로벌컴퓨팅",
      "hrNo": "0056592",
      "meet": "서울",
      "name": "미국",
      "owName": "장재형",
      "owNo": "010611",
      "pgDate": "20260530",
      "pgNo": "8",
      "prdName": "Jeff&Melissa Prunzik",
      "prizeCond": "R0~50",
      "rank": "혼4등급",
      "rcCntY": "5",
      "rcDist": "1800",
      "rcName": "일반",
      "sex": "거",
      "trName": "전승규",
      "trNo": "070182",
      "recentRating": "39"
    }
  ]
}